kitsat/__init__.py
kitsat/kitsat_cli.py
kitsat/pyvenv.cfg
kitsat/Scripts/Activate.ps1
kitsat/Scripts/activate
kitsat/Scripts/activate.bat
kitsat/Scripts/deactivate.bat
kitsat/Scripts/pip.exe
kitsat/Scripts/pip3.11.exe
kitsat/Scripts/pip3.exe
kitsat/Scripts/python.exe
kitsat/Scripts/pythonw.exe
kitsat/cfg/__init__.py
kitsat/cfg/cli_commands.csv
kitsat/cfg/sat_commands.csv
kitsat/lib/__init__.py
kitsat/lib/cmd_parser.py
kitsat/lib/math_utils.py
kitsat/lib/modem.py
kitsat/lib/packet_parser.py
kitsat/lib/site-packages/distutils-precedence.pth
kitsat/lib/site-packages/_distutils_hack/__init__.py
kitsat/lib/site-packages/_distutils_hack/override.py
kitsat/lib/site-packages/pip/__init__.py
kitsat/lib/site-packages/pip/__main__.py
kitsat/lib/site-packages/pip/__pip-runner__.py
kitsat/lib/site-packages/pip/py.typed
kitsat/lib/site-packages/pip/_internal/__init__.py
kitsat/lib/site-packages/pip/_internal/build_env.py
kitsat/lib/site-packages/pip/_internal/cache.py
kitsat/lib/site-packages/pip/_internal/configuration.py
kitsat/lib/site-packages/pip/_internal/exceptions.py
kitsat/lib/site-packages/pip/_internal/main.py
kitsat/lib/site-packages/pip/_internal/pyproject.py
kitsat/lib/site-packages/pip/_internal/self_outdated_check.py
kitsat/lib/site-packages/pip/_internal/wheel_builder.py
kitsat/lib/site-packages/pip/_internal/cli/__init__.py
kitsat/lib/site-packages/pip/_internal/cli/autocompletion.py
kitsat/lib/site-packages/pip/_internal/cli/base_command.py
kitsat/lib/site-packages/pip/_internal/cli/cmdoptions.py
kitsat/lib/site-packages/pip/_internal/cli/command_context.py
kitsat/lib/site-packages/pip/_internal/cli/main.py
kitsat/lib/site-packages/pip/_internal/cli/main_parser.py
kitsat/lib/site-packages/pip/_internal/cli/parser.py
kitsat/lib/site-packages/pip/_internal/cli/progress_bars.py
kitsat/lib/site-packages/pip/_internal/cli/req_command.py
kitsat/lib/site-packages/pip/_internal/cli/spinners.py
kitsat/lib/site-packages/pip/_internal/cli/status_codes.py
kitsat/lib/site-packages/pip-23.1.2.dist-info/AUTHORS.txt
kitsat/lib/site-packages/pip-23.1.2.dist-info/INSTALLER
kitsat/lib/site-packages/pip-23.1.2.dist-info/LICENSE.txt
kitsat/lib/site-packages/pip-23.1.2.dist-info/METADATA
kitsat/lib/site-packages/pip-23.1.2.dist-info/RECORD
kitsat/lib/site-packages/pip-23.1.2.dist-info/REQUESTED
kitsat/lib/site-packages/pip-23.1.2.dist-info/WHEEL
kitsat/lib/site-packages/pip-23.1.2.dist-info/entry_points.txt
kitsat/lib/site-packages/pip-23.1.2.dist-info/top_level.txt
kitsat/lib/site-packages/setuptools-65.5.0.dist-info/INSTALLER
kitsat/lib/site-packages/setuptools-65.5.0.dist-info/LICENSE
kitsat/lib/site-packages/setuptools-65.5.0.dist-info/METADATA
kitsat/lib/site-packages/setuptools-65.5.0.dist-info/RECORD
kitsat/lib/site-packages/setuptools-65.5.0.dist-info/REQUESTED
kitsat/lib/site-packages/setuptools-65.5.0.dist-info/WHEEL
kitsat/lib/site-packages/setuptools-65.5.0.dist-info/entry_points.txt
kitsat/lib/site-packages/setuptools-65.5.0.dist-info/top_level.txt
kitsat-1.2.15.dist-info/METADATA
kitsat-1.2.15.dist-info/WHEEL
kitsat-1.2.15.dist-info/entry_points.txt
kitsat-1.2.15.dist-info/licenses/LICENSE.md
kitsat-1.2.15.dist-info/RECORD
