Metadata-Version: 2.1
Name: kitsat
Version: 1.2.15
Summary: CLI and python library for communicating with the Kitsat educational satellite
Project-URL: Homepage, https://github.com/netnspace/Kitsat-Python-Library
Author-email: Tuomas Simula <tuomas@simu.la>, Samuli Nyman <samuli@kitsat.fi>, Tessa Nikander <tessa@kitsat.fi>
License:                     GNU GENERAL PUBLIC LICENSE
License-File: LICENSE.md
Classifier: License :: OSI Approved :: GNU General Public License v3 or later (GPLv3+)
Classifier: Operating System :: OS Independent
Classifier: Programming Language :: Python :: 3
Requires-Python: >=3.4
Requires-Dist: blessed>=1.16.0
Requires-Dist: pyserial>=3.0
